enigma_cipher/__init__.py
enigma_cipher/enigma_machine.py
enigma_cipher/components/__init__.py
enigma_cipher/components/characters.py
enigma_cipher/components/plug_board.py
enigma_cipher/components/reflector.py
enigma_cipher/components/rotor.py
enigma_cipher-1.1.0.dist-info/LICENSE
enigma_cipher-1.1.0.dist-info/METADATA
enigma_cipher-1.1.0.dist-info/WHEEL
enigma_cipher-1.1.0.dist-info/top_level.txt
enigma_cipher-1.1.0.dist-info/RECORD
