Metadata-Version: 2.1
Name: enigma-cipher
Version: 1.1.0
Summary: Package providing encoder and decoder instances to use the enigma machine cipher
Home-page: https://github.com/Jtachan/enigma_cipher.git
Author: Jaime Gonzalez Gomez
Author-email: jim.gomez.dnn@gmail.com
Requires-Python: >=3.8
License-File: LICENSE
